ecomus/__init__.py
ecomus/data_parser.py
ecomus/emoji-data.txt
ecomus/models.py
ecomus/parser.py
ecomus/pattern.py
ecomus/pattern_template.py
ecomus/utils.py
ecomus/ywr.pyz
ecomus-1.2.4.dist-info/METADATA
ecomus-1.2.4.dist-info/WHEEL
ecomus-1.2.4.dist-info/top_level.txt
ecomus-1.2.4.dist-info/RECORD
