Metadata-Version: 2.1
Name: ecomus
Version: 1.2.4
Summary: Replace unicode emojis by its corresponding image representation. supports unicode 9 standard.
Author: kubet
Author-email: kubet@atomicmail.io
License: Apache License 2.0
